hassan_in_matrix/__init__.py
hassan_in_matrix/matrix.py
hassan_in_matrix/utils.py
hassan_in_matrix-0.0.5.dist-info/METADATA
hassan_in_matrix-0.0.5.dist-info/WHEEL
hassan_in_matrix-0.0.5.dist-info/licenses/LICENSE.md
hassan_in_matrix-0.0.5.dist-info/RECORD
